numstat.py
numstat-0.2.0.dist-info/METADATA
numstat-0.2.0.dist-info/WHEEL
numstat-0.2.0.dist-info/RECORD
