Metadata-Version: 2.1
Name: numstat
Version: 0.2.0
Summary: 
Author: alex_past_15
Requires-Python: >=3.11,<4.0
Classifier: Programming Language :: Python :: 3
Classifier: Programming Language :: Python :: 3.11
Classifier: Programming Language :: Python :: 3.12
